remake/__init__.py
remake/bcolors.py
remake/flags.py
remake/formatter.py
remake/load_remake.py
remake/metadata.py
remake/monitor.py
remake/remake_base.py
remake/remake_cmd.py
remake/remake_exceptions.py
remake/setup_logging.py
remake/special_paths.py
remake/task.py
remake/task_control.py
remake/task_query_set.py
remake/task_rule.py
remake/util.py
remake/version.py
remake/examples/Makefile
remake/examples/README.md
remake/examples/__init__.py
remake/examples/demo.py
remake/examples/ex1.1.py
remake/examples/ex1.2.py
remake/examples/ex1.py
remake/examples/ex2.py
remake/examples/ex3.py
remake/examples/ex4.py
remake/examples/ex5.py
remake/examples/ex6.py
remake/examples/ex7.py
remake/examples/ex8.py
remake/examples/ex_slurm.py
remake/examples/remakefile.py
remake/examples/data/in.txt
remake/examples/data/inputs/a.00.in
remake/examples/data/inputs/a.01.in
remake/examples/data/inputs/a.02.in
remake/examples/data/inputs/a.10.in
remake/examples/data/inputs/a.11.in
remake/examples/data/inputs/a.12.in
remake/examples/data/inputs/a.in
remake/examples/data/inputs/b.in
remake/examples/data/inputs/c.in
remake/examples/data/inputs/ex8_in1.txt
remake/examples/data/inputs/in1.txt
remake/examples/data/inputs/in2.txt
remake/executor/__init__.py
remake/executor/base_executor.py
remake/executor/multiproc_executor.py
remake/executor/singleproc_executor.py
remake/executor/slurm_executor.py
remake/experimental/__init__.py
remake/experimental/networkx_displays.py
remake-0.6.1.dist-info/LICENCE
remake-0.6.1.dist-info/METADATA
remake-0.6.1.dist-info/WHEEL
remake-0.6.1.dist-info/entry_points.txt
remake-0.6.1.dist-info/top_level.txt
remake-0.6.1.dist-info/RECORD
