Metadata-Version: 2.1
Name: remake
Version: 0.6.1
Summary: Smart remake tool
Home-page: https://github.com/markmuetz/remake
Author: Mark Muetzelfeldt
Author-email: mark.muetzelfeldt@reading.ac.uk
Maintainer: Mark Muetzelfeldt
Maintainer-email: mark.muetzelfeldt@reading.ac.uk
License: LICENSE
Project-URL: Documentation, https://markmuetz.github.io/remake
Project-URL: Bug Tracker, https://github.com/markmuetz/remake/issues
Platform: UNKNOWN
Classifier: Environment :: Console
Classifier: Intended Audience :: Science/Research
Classifier: Natural Language :: English
Classifier: Operating System :: POSIX :: Linux
Classifier: Programming Language :: Python :: 3.9
Classifier: Development Status :: 4 - Beta
Requires-Python: >=3.6
Requires-Dist: networkx
Requires-Dist: tabulate
Provides-Extra: debug
Requires-Dist: ipdb ; extra == 'debug'
Provides-Extra: display
Requires-Dist: matplotlib ; extra == 'display'
Provides-Extra: experimental
Requires-Dist: numpy ; extra == 'experimental'
Provides-Extra: testing
Requires-Dist: nose ; extra == 'testing'
Requires-Dist: coverage ; extra == 'testing'
Requires-Dist: numpy ; extra == 'testing'
Requires-Dist: matplotlib ; extra == 'testing'
